hacs_utils/__init__.py
hacs_utils/adapter.py
hacs_utils/agent_types.py
hacs_utils/compatibility.py
hacs_utils/container.py
hacs_utils/core_utils.py
hacs_utils/integration_types.py
hacs_utils/py.typed
hacs_utils/structured.py
hacs_utils/agents/chat_cli.py
hacs_utils/agents/mcp_client.py
hacs_utils/integrations/__init__.py
hacs_utils/integrations/framework_adapter.py
hacs_utils/integrations/anthropic/__init__.py
hacs_utils/integrations/common/__init__.py
hacs_utils/integrations/common/tool_loader.py
hacs_utils/integrations/crewai/__init__.py
hacs_utils/integrations/crewai/adapter.py
hacs_utils/integrations/langchain/README.md
hacs_utils/integrations/langchain/__init__.py
hacs_utils/integrations/langchain/adapters.py
hacs_utils/integrations/langchain/agents.py
hacs_utils/integrations/langchain/chains.py
hacs_utils/integrations/langchain/memory.py
hacs_utils/integrations/langchain/retrievers.py
hacs_utils/integrations/langchain/tools.py
hacs_utils/integrations/langchain/vector_stores.py
hacs_utils/integrations/langchain/examples/README.md
hacs_utils/integrations/langgraph/__init__.py
hacs_utils/integrations/langgraph/custom_tools.py
hacs_utils/integrations/langgraph/hacs_agent_tools.py
hacs_utils/integrations/langgraph/hil.py
hacs_utils/integrations/openai/__init__.py
hacs_utils/integrations/openai/client.py
hacs_utils/integrations/openai/embedding.py
hacs_utils/integrations/openai/factory.py
hacs_utils/integrations/pinecone/__init__.py
hacs_utils/integrations/pinecone/store.py
hacs_utils/integrations/qdrant/__init__.py
hacs_utils/integrations/qdrant/store.py
hacs_utils/mcp/__init__.py
hacs_utils/mcp/cli.py
hacs_utils/mcp/fastmcp_server.py
hacs_utils/mcp/messages.py
hacs_utils/mcp/server.py
hacs_utils/mcp/tools.py
hacs_utils/mcp/transport.py
hacs_utils-0.4.3.dist-info/METADATA
hacs_utils-0.4.3.dist-info/WHEEL
hacs_utils-0.4.3.dist-info/entry_points.txt
hacs_utils-0.4.3.dist-info/RECORD
