Metadata-Version: 2.4
Name: hacs-utils
Version: 0.4.3
Summary: External service integrations, utilities, and MCP server for HACS
Project-URL: Homepage, https://github.com/solanovisitor/hacs-ai
Project-URL: Documentation, https://github.com/solanovisitor/hacs-ai/blob/main/docs/
Project-URL: Repository, https://github.com/solanovisitor/hacs-ai
Project-URL: Issues, https://github.com/solanovisitor/hacs-ai/issues
Project-URL: Changelog, https://github.com/solanovisitor/hacs-ai/blob/main/CHANGELOG.md
Author-email: Solano Todeschini <solanovisitor@gmail.com>
Maintainer-email: Solano Todeschini <solanovisitor@gmail.com>
License: MIT
Keywords: agents,ai,anthropic,crewai,healthcare,langchain,langgraph,mcp,model-context-protocol,openai,pinecone,qdrant,utils
Classifier: Development Status :: 4 - Beta
Classifier: Intended Audience :: Developers
Classifier: Intended Audience :: Healthcare Industry
Classifier: License :: OSI Approved :: MIT License
Classifier: Programming Language :: Python :: 3
Classifier: Programming Language :: Python :: 3.11
Classifier: Programming Language :: Python :: 3.12
Classifier: Topic :: Scientific/Engineering :: Medical Science Apps.
Classifier: Topic :: Software Development :: Libraries :: Python Modules
Classifier: Typing :: Typed
Requires-Python: >=3.11
Requires-Dist: fastapi>=0.116.1
Requires-Dist: hacs-core>=0.4.3
Requires-Dist: hacs-registry>=0.4.3
Requires-Dist: langchain-community<0.4.0,>=0.3.0
Requires-Dist: langchain-core<0.4.0,>=0.3.0
Requires-Dist: langchain-mcp-adapters>=0.1.9
Requires-Dist: langchain<0.4.0,>=0.3.0
Requires-Dist: mcp>=1.1.2
Requires-Dist: psycopg[binary,pool]>=3.2.9
Requires-Dist: pydantic<3.0.0,>=2.11.0
Requires-Dist: pyyaml>=6.0.0
Requires-Dist: qdrant-client>=1.15.1
Requires-Dist: requests>=2.32.4
Requires-Dist: uvicorn[standard]>=0.35.0
Provides-Extra: agents
Requires-Dist: fastapi>=0.116.1; extra == 'agents'
Requires-Dist: langchain-community<0.4.0,>=0.3.0; extra == 'agents'
Requires-Dist: langchain-core<0.4.0,>=0.3.0; extra == 'agents'
Requires-Dist: langchain-openai>=0.1.7; extra == 'agents'
Requires-Dist: langchain<0.4.0,>=0.3.0; extra == 'agents'
Requires-Dist: langgraph>=0.6.2; extra == 'agents'
Requires-Dist: uvicorn[standard]>=0.35.0; extra == 'agents'
Provides-Extra: ai
Requires-Dist: anthropic>=0.60.0; extra == 'ai'
Requires-Dist: instructor>=1.3.0; extra == 'ai'
Requires-Dist: openai>=1.98.0; extra == 'ai'
Provides-Extra: all
Requires-Dist: anthropic>=0.60.0; extra == 'all'
Requires-Dist: crewai>=0.22.0; extra == 'all'
Requires-Dist: fastapi>=0.110.0; extra == 'all'
Requires-Dist: fastapi>=0.116.1; extra == 'all'
Requires-Dist: instructor>=1.3.0; extra == 'all'
Requires-Dist: langchain-community<0.4.0,>=0.3.0; extra == 'all'
Requires-Dist: langchain-core<0.4.0,>=0.3.0; extra == 'all'
Requires-Dist: langchain-openai>=0.1.7; extra == 'all'
Requires-Dist: langchain<0.4.0,>=0.3.0; extra == 'all'
Requires-Dist: langgraph>=0.6.2; extra == 'all'
Requires-Dist: openai>=1.98.0; extra == 'all'
Requires-Dist: pinecone>=7.3.0; extra == 'all'
Requires-Dist: psycopg2-binary>=2.9.0; extra == 'all'
Requires-Dist: python-dotenv>=1.0.0; extra == 'all'
Requires-Dist: qdrant-client>=1.15.1; extra == 'all'
Requires-Dist: sqlalchemy>=2.0.0; extra == 'all'
Requires-Dist: uvicorn[standard]>=0.29.0; extra == 'all'
Requires-Dist: uvicorn[standard]>=0.35.0; extra == 'all'
Provides-Extra: anthropic
Requires-Dist: anthropic>=0.60.0; extra == 'anthropic'
Provides-Extra: crewai
Requires-Dist: crewai>=0.22.0; extra == 'crewai'
Provides-Extra: dev
Requires-Dist: black>=23.0.0; extra == 'dev'
Requires-Dist: mypy>=1.8.0; extra == 'dev'
Requires-Dist: pytest-asyncio>=0.21.0; extra == 'dev'
Requires-Dist: pytest-cov>=4.0.0; extra == 'dev'
Requires-Dist: pytest>=7.0.0; extra == 'dev'
Requires-Dist: ruff>=0.4.0; extra == 'dev'
Provides-Extra: langchain
Requires-Dist: langchain-community<0.4.0,>=0.3.0; extra == 'langchain'
Requires-Dist: langchain-core<0.4.0,>=0.3.0; extra == 'langchain'
Requires-Dist: langchain-openai>=0.1.7; extra == 'langchain'
Requires-Dist: langchain<0.4.0,>=0.3.0; extra == 'langchain'
Provides-Extra: langgraph
Requires-Dist: langgraph>=0.6.2; extra == 'langgraph'
Provides-Extra: mcp
Requires-Dist: fastapi>=0.110.0; extra == 'mcp'
Requires-Dist: python-dotenv>=1.0.0; extra == 'mcp'
Requires-Dist: uvicorn[standard]>=0.29.0; extra == 'mcp'
Provides-Extra: openai
Requires-Dist: instructor>=1.3.0; extra == 'openai'
Requires-Dist: openai>=1.98.0; extra == 'openai'
Provides-Extra: pinecone
Requires-Dist: pinecone>=7.3.0; extra == 'pinecone'
Provides-Extra: postgres
Requires-Dist: psycopg2-binary>=2.9.0; extra == 'postgres'
Requires-Dist: sqlalchemy>=2.0.0; extra == 'postgres'
Provides-Extra: qdrant
Requires-Dist: qdrant-client>=1.15.1; extra == 'qdrant'
Provides-Extra: vector
Requires-Dist: pinecone>=7.3.0; extra == 'vector'
Requires-Dist: qdrant-client>=1.15.1; extra == 'vector'
Provides-Extra: workflows
Requires-Dist: crewai>=0.22.0; extra == 'workflows'
Requires-Dist: langchain-community<0.4.0,>=0.3.0; extra == 'workflows'
Requires-Dist: langchain-core<0.4.0,>=0.3.0; extra == 'workflows'
Requires-Dist: langchain-openai>=0.1.7; extra == 'workflows'
Requires-Dist: langchain<0.4.0,>=0.3.0; extra == 'workflows'
Requires-Dist: langgraph>=0.6.2; extra == 'workflows'
